<Properties StartupConfiguration="{6F3CDE36-89C4-44B6-9CBB-A47A522BB189}|Default">
  <MonoDevelop.Ide.Workbench ActiveDocument="Produto.cs">
    <Files>
      <File FileName="Program.cs" Line="11" Column="6" />
      <File FileName="Produto.cs" Line="6" Column="1" />
    </Files>
    <Pads>
      <Pad Id="ProjectPad">
        <State name="__root__">
          <Node name="Construtor" expanded="True">
            <Node name="Construtor" expanded="True">
              <Node name="Produto.cs" selected="True" />
            </Node>
          </Node>
        </State>
      </Pad>
    </Pads>
  </MonoDevelop.Ide.Workbench>
  <MonoDevelop.Ide.DebuggingService.PinnedWatches />
  <MonoDevelop.Ide.Workspace ActiveConfiguration="Debug" />
  <MonoDevelop.Ide.ItemProperties.Construtor FirstBuild="True" PreferredExecutionTarget="MonoDevelop.Default" />
  <MonoDevelop.Ide.DebuggingService.Breakpoints>
    <BreakpointStore />
  </MonoDevelop.Ide.DebuggingService.Breakpoints>
  <MultiItemStartupConfigurations />
</Properties>